Metadata-Version: 1.1
Name: django-fcm
Version: 0.0.9
Summary: A Django package that enables sending messages using FCM (Firebase Cloud Messaging).
Home-page: https://django-fcm.readthedocs.io/en/latest/
Author: Chitrank Dixit
Author-email: chitrankdixit@gmail.com
License: MIT License
Platform: any
Classifier: Environment :: Web Environment
Classifier: Framework :: Django
Classifier: Framework :: Django :: 1.9
Classifier: Intended Audience :: Developers
Classifier: License :: OSI Approved :: BSD License
Classifier: Operating System :: OS Independent
Classifier: Programming Language :: Python
Classifier: Programming Language :: Python :: 3
Classifier: Programming Language :: Python :: 3.4
Classifier: Programming Language :: Python :: 3.5
Classifier: Topic :: Internet :: WWW/HTTP
Classifier: Topic :: Internet :: WWW/HTTP :: Dynamic Content
